ai/backend/runner/.bash_profile
ai/backend/runner/.bashrc
ai/backend/runner/.tmux.conf
ai/backend/runner/.vimrc
ai/backend/runner/.zshrc
ai/backend/runner/DO_NOT_STORE_PERSISTENT_FILES_HERE.md
ai/backend/runner/README.md
ai/backend/runner/VERSION
ai/backend/runner/__init__.py
ai/backend/runner/all-smi.1
ai/backend/runner/all-smi.aarch64.bin
ai/backend/runner/bssh.1
ai/backend/runner/bssh.aarch64.bin
ai/backend/runner/default-seccomp.json
ai/backend/runner/dropbearmulti.aarch64.bin
ai/backend/runner/entrypoint.sh
ai/backend/runner/extract_dotfiles.py
ai/backend/runner/fantompass.py
ai/backend/runner/hash_phrase.py
ai/backend/runner/jupyter-custom.css
ai/backend/runner/krunner-extractor.img.aarch64.tar.xz
ai/backend/runner/krunner-extractor.sh
ai/backend/runner/libbaihook.alpine3.8.aarch64.so
ai/backend/runner/libbaihook.centos7.6.aarch64.so
ai/backend/runner/libbaihook.centos7.9.aarch64.so
ai/backend/runner/libbaihook.centos8.0.aarch64.so
ai/backend/runner/libbaihook.ubuntu18.04.aarch64.so
ai/backend/runner/libbaihook.ubuntu20.04.aarch64.so
ai/backend/runner/libbaihook.ubuntu22.04.aarch64.so
ai/backend/runner/logo.svg
ai/backend/runner/roboto-italic.ttf
ai/backend/runner/roboto.ttf
ai/backend/runner/sftp-server.aarch64.bin
ai/backend/runner/su-exec.aarch64.bin
ai/backend/runner/tmux.aarch64.bin
ai/backend/runner/ttyd_linux.aarch64.bin
ai/backend/runner/words.json
ai/backend/runner/yank.sh
ai/backend/runner/terminfo.alpine3.8/s/screen
ai/backend/runner/terminfo.alpine3.8/s/screen-256color
ai/backend/runner/terminfo.alpine3.8/s/screen.xterm-256color
ai/backend/runner/terminfo.alpine3.8/x/xterm
ai/backend/runner/terminfo.alpine3.8/x/xterm+256color
ai/backend/runner/terminfo.alpine3.8/x/xterm-256color
backend_ai_kernel_binary-26.1.0.dist-info/METADATA
backend_ai_kernel_binary-26.1.0.dist-info/WHEEL
backend_ai_kernel_binary-26.1.0.dist-info/namespace_packages.txt
backend_ai_kernel_binary-26.1.0.dist-info/top_level.txt
backend_ai_kernel_binary-26.1.0.dist-info/RECORD
